sqlmodel_gcp_postgres/__init__.py
sqlmodel_gcp_postgres/db.py
sqlmodel_gcp_postgres/py.typed
sqlmodel_gcp_postgres-1.0.1.dist-info/METADATA
sqlmodel_gcp_postgres-1.0.1.dist-info/WHEEL
sqlmodel_gcp_postgres-1.0.1.dist-info/licenses/LICENSE
sqlmodel_gcp_postgres-1.0.1.dist-info/RECORD
