Metadata-Version: 2.4
Name: sqlmodel-gcp-postgres
Version: 1.0.1
Summary: SQLModel ORM integration for Google Cloud SQL PostgreSQL with multi-database support
Project-URL: Homepage, https://github.com/CodifyIQ/sqlmodel-gcp-postgres
Project-URL: Repository, https://github.com/CodifyIQ/sqlmodel-gcp-postgres
Project-URL: Issues, https://github.com/CodifyIQ/sqlmodel-gcp-postgres/issues
Author-email: Eric Konieczny <eric.konieczny@codifyiq.com>
License: MIT
License-File: LICENSE
Keywords: cloud-sql,google-cloud,orm,postgresql,sqlmodel
Classifier: Development Status :: 4 - Beta
Classifier: Intended Audience :: Developers
Classifier: License :: OSI Approved :: MIT License
Classifier: Operating System :: OS Independent
Classifier: Programming Language :: Python :: 3
Classifier: Programming Language :: Python :: 3.12
Classifier: Programming Language :: Python :: 3.13
Classifier: Topic :: Database
Requires-Python: >=3.12
Requires-Dist: cloud-sql-python-connector[pg8000]>=1.18.0
Requires-Dist: loguru>=0.7.0
Requires-Dist: sqlmodel>=0.0.20
